{
  "items": [
    {
      "id": "cfe8f944-72cd-4c17-92fb-5432a4b08e9b",
      "ticketId": "55cc1598-5a93-41da-9a73-36a59b90edf3",
      "type": "CREATED",
      "payload": {
        "title": "Chamado comentário 1771460447965"
      },
      "actorUserId": "usr_admin",
      "createdAt": "2026-02-19T00:20:57.493Z"
    },
    {
      "id": "60974570-d5b7-4959-a959-d64e787b1d61",
      "ticketId": "71a4989f-62bf-41c0-a03a-9679462a0c9c",
      "type": "CREATED",
      "payload": {
        "title": "Chamado comentário 1771460354311"
      },
      "actorUserId": "usr_admin",
      "createdAt": "2026-02-19T00:19:23.742Z"
    },
    {
      "id": "e2dd0802-1512-4714-b01d-2d3b7fb575cd",
      "ticketId": "3959f535-6f8c-45ac-9796-cfa5659adda2",
      "type": "CREATED",
      "payload": {
        "title": "Automated chamado admin-1771460253529"
      },
      "actorUserId": "usr_admin",
      "createdAt": "2026-02-19T00:17:45.351Z"
    },
    {
      "id": "2a1902e1-aa03-4fb4-b29a-69fde44c7a53",
      "ticketId": "2accf721-5004-4197-89b7-0018903b14ad",
      "type": "CREATED",
      "payload": {
        "title": "Automated chamado admin-1771460220496"
      },
      "actorUserId": "usr_admin",
      "createdAt": "2026-02-19T00:17:07.166Z"
    },
    {
      "id": "70323d08-6e4d-482d-8878-a57bd8f46630",
      "ticketId": "34d5ccda-68c1-4f0a-adf4-fc15ba91fef5",
      "type": "CREATED",
      "payload": {
        "title": "Chamado comentário 1771459635896"
      },
      "actorUserId": "usr_admin",
      "createdAt": "2026-02-19T00:07:43.897Z"
    },
    {
      "id": "c464a4da-e498-45d8-9c61-c5fa48a85fa2",
      "ticketId": "8b7f205e-72fc-4e17-b21e-ec92fa193ea2",
      "type": "CREATED",
      "payload": {
        "title": "Chamado comentário 1771459539449"
      },
      "actorUserId": "usr_admin",
      "createdAt": "2026-02-19T00:06:04.568Z"
    },
    {
      "id": "0b3ec383-cf7d-4c77-b96f-ba446eb89141",
      "ticketId": "bebf7836-1e90-4cb6-b07f-d01ec3518132",
      "type": "CREATED",
      "payload": {
        "title": "Automated chamado admin-1771459301134"
      },
      "actorUserId": "usr_admin",
      "createdAt": "2026-02-19T00:02:12.805Z"
    },
    {
      "id": "b0693967-59e1-4fd2-b0be-18f9b88c7f4d",
      "ticketId": "feed9bdb-cdbe-4816-88b3-19462c04881c",
      "type": "CREATED",
      "payload": {
        "title": "Automated chamado admin-1771459255078"
      },
      "actorUserId": "usr_admin",
      "createdAt": "2026-02-19T00:01:08.733Z"
    },
    {
      "id": "aaddd10b-7ac2-4274-a6f2-d3354761b174",
      "ticketId": "498b0a99-a0ef-4863-a6b4-7a433cd5fe25",
      "type": "CREATED",
      "payload": {
        "title": "Chamado Público"
      },
      "actorUserId": "anonymous",
      "createdAt": "2026-02-18T23:47:30.435Z"
    },
    {
      "id": "1f77fb1f-061e-4b07-83c7-73a7448be75f",
      "ticketId": "6201b4e9-0232-43a6-82f7-6b7bda83d4f2",
      "type": "CREATED",
      "payload": {
        "title": "Chamado comentário 1771455073790"
      },
      "actorUserId": "usr_admin",
      "createdAt": "2026-02-18T22:51:27.471Z"
    },
    {
      "id": "28df11d3-5345-49bc-b5e7-e908d01a0f45",
      "ticketId": "02015597-cad4-4f61-8285-e6339bace4f1",
      "type": "CREATED",
      "payload": {
        "title": "Chamado comentário 1771454978942"
      },
      "actorUserId": "usr_admin",
      "createdAt": "2026-02-18T22:49:50.588Z"
    },
    {
      "id": "04e517ca-beba-4e26-ae12-9babd863a982",
      "ticketId": "738a35f8-f7cf-4afa-8ec3-3f0e59264607",
      "type": "CREATED",
      "payload": {
        "title": "Automated chamado admin-1771454858812"
      },
      "actorUserId": "usr_admin",
      "createdAt": "2026-02-18T22:47:55.209Z"
    },
    {
      "id": "a0c9ff94-88e5-4a0d-bae8-b3a35d52fffd",
      "ticketId": "2ccc9695-8a01-4aac-81ca-fa4bfc577e67",
      "type": "CREATED",
      "payload": {
        "title": "Automated chamado admin-1771454822676"
      },
      "actorUserId": "usr_admin",
      "createdAt": "2026-02-18T22:47:11.672Z"
    },
    {
      "id": "4efac3bf-720f-4f6a-8df1-319e03c7fcbb",
      "ticketId": "0c5f033c-c340-4f2e-af68-ee477dc24f64",
      "type": "CREATED",
      "payload": {
        "title": "Chamado Público"
      },
      "actorUserId": "anonymous",
      "createdAt": "2026-02-18T22:41:51.535Z"
    },
    {
      "id": "48bcaffa-b629-49ff-8379-f12c67f7f6fd",
      "ticketId": "66f2f658-9b11-4ff0-95e0-b2c2606501db",
      "type": "CREATED",
      "payload": {
        "title": "Chamado Público"
      },
      "actorUserId": "anonymous",
      "createdAt": "2026-02-18T22:41:09.270Z"
    },
    {
      "id": "cb948cf0-22eb-4068-bff0-b9f2cf8da244",
      "ticketId": "927dd799-ae5c-46ef-ad5c-f62e5d81f6c3",
      "type": "CREATED",
      "payload": {
        "title": "Chamado comentário 1771453082426"
      },
      "actorUserId": "usr_admin",
      "createdAt": "2026-02-18T22:18:10.519Z"
    },
    {
      "id": "5849f11f-105a-421f-acb9-6b6075f6c880",
      "ticketId": "e1297dbe-bdd9-45e8-b93f-04d2845ea7a1",
      "type": "CREATED",
      "payload": {
        "title": "Chamado comentário 1771452989336"
      },
      "actorUserId": "usr_admin",
      "createdAt": "2026-02-18T22:16:36.861Z"
    },
    {
      "id": "2b637757-bc27-4776-b2da-249fe30701dc",
      "ticketId": "930d736e-966c-4bc6-a754-451dfffadbb8",
      "type": "CREATED",
      "payload": {
        "title": "Automated chamado admin-1771452892705"
      },
      "actorUserId": "usr_admin",
      "createdAt": "2026-02-18T22:15:02.247Z"
    },
    {
      "id": "6fecb004-e329-4ea0-a3ba-e4c5f41e93cd",
      "ticketId": "607c707c-08b9-41fd-99fb-cb4d203701c0",
      "type": "CREATED",
      "payload": {
        "title": "Automated chamado admin-1771452848626"
      },
      "actorUserId": "usr_admin",
      "createdAt": "2026-02-18T22:14:22.756Z"
    },
    {
      "id": "ad2d2ff8-c3e3-4163-8aa3-c54381032391",
      "ticketId": "391a6be7-9f32-437f-8b5f-f00f90d55b6e",
      "type": "CREATED",
      "payload": {
        "title": "Chamado Público"
      },
      "actorUserId": "anonymous",
      "createdAt": "2026-02-18T21:38:57.874Z"
    },
    {
      "id": "90b54821-e8ad-4bcc-827a-1ef0c4aeccfd",
      "ticketId": "a219f547-4011-409c-8ed7-01d5954f1c38",
      "type": "CREATED",
      "payload": {
        "title": "Chamado Público"
      },
      "actorUserId": "anonymous",
      "createdAt": "2026-02-18T21:03:55.406Z"
    },
    {
      "id": "ef02216c-999e-4939-bce1-d78aae317a1b",
      "ticketId": "15cac611-b5a5-47d8-91be-02de5641ceee",
      "type": "CREATED",
      "payload": {
        "title": "Chamado Público"
      },
      "actorUserId": "anonymous",
      "createdAt": "2026-02-18T21:03:13.158Z"
    },
    {
      "id": "a2385c4e-4eb9-4b9b-9ccd-12b4ce18796d",
      "ticketId": "efd0385a-3734-4b91-9fd5-e85be83dc60a",
      "type": "CREATED",
      "payload": {
        "title": "Chamado Público"
      },
      "actorUserId": "anonymous",
      "createdAt": "2026-02-18T21:02:34.166Z"
    },
    {
      "id": "2cd016fe-0093-46a4-ad01-24b7fee5bd0f",
      "ticketId": "3e11120e-3eea-4bf4-8211-7dd7de90cc37",
      "type": "CREATED",
      "payload": {
        "title": "Chamado Público"
      },
      "actorUserId": "anonymous",
      "createdAt": "2026-02-18T21:01:51.351Z"
    },
    {
      "id": "f40c18d0-ed2a-4a6f-aa49-b5ede1ee6986",
      "ticketId": "d5b1a664-be75-4c44-8e8d-43ddf6c87cf7",
      "type": "CREATED",
      "payload": {
        "title": "Chamado Público"
      },
      "actorUserId": "anonymous",
      "createdAt": "2026-02-18T21:00:29.910Z"
    },
    {
      "id": "8299e2a4-af02-4ec0-8d22-e6e2aeb7d2ad",
      "ticketId": "9d859d82-8bf4-4186-8b7a-9bc13f8c8506",
      "type": "CREATED",
      "payload": {
        "title": "njnjnj"
      },
      "actorUserId": "usr_admin",
      "createdAt": "2026-02-18T00:40:29.937Z"
    },
    {
      "id": "78bdeffc-b51c-47fc-8381-385b713a2135",
      "ticketId": "64e1ca96-0168-46dc-b3a9-160109cbd6d6",
      "type": "STATUS_CHANGED",
      "payload": {
        "from": "review",
        "to": "done",
        "reason": null
      },
      "actorUserId": "usr_admin",
      "createdAt": "2026-02-17T23:34:07.802Z"
    },
    {
      "id": "4bed3e5c-cdc1-4273-bd2d-9987fe54f5c8",
      "ticketId": "28d3f8fa-a261-49ee-a8c6-706f51f5764f",
      "type": "STATUS_CHANGED",
      "payload": {
        "from": "review",
        "to": "done",
        "reason": null
      },
      "actorUserId": "usr_admin",
      "createdAt": "2026-02-17T23:33:56.922Z"
    },
    {
      "id": "e4b9bf82-9fdb-4627-af34-b06347953908",
      "ticketId": "64e1ca96-0168-46dc-b3a9-160109cbd6d6",
      "type": "STATUS_CHANGED",
      "payload": {
        "from": "done",
        "to": "review",
        "reason": null
      },
      "actorUserId": "usr_admin",
      "createdAt": "2026-02-17T23:33:55.075Z"
    },
    {
      "id": "6b979e9d-f84e-489a-97b9-929141cbbc8f",
      "ticketId": "28d3f8fa-a261-49ee-a8c6-706f51f5764f",
      "type": "STATUS_CHANGED",
      "payload": {
        "from": "doing",
        "to": "review",
        "reason": null
      },
      "actorUserId": "usr_admin",
      "createdAt": "2026-02-17T23:33:44.892Z"
    },
    {
      "id": "ed746ff8-8816-4e4c-ae29-4c76618fa9ed",
      "ticketId": "7608629f-f2b3-4ea1-a932-5cacaf0f520c",
      "type": "CREATED",
      "payload": {
        "title": "Chamado comentário 1771359863282"
      },
      "actorUserId": "usr_admin",
      "createdAt": "2026-02-17T20:24:43.438Z"
    },
    {
      "id": "5dc14875-e7d1-4de4-88d4-a4a119aa90e3",
      "ticketId": "93afc640-cbb6-45c7-8d18-4c06700efecc",
      "type": "CREATED",
      "payload": {
        "title": "Chamado comentário 1771359752735"
      },
      "actorUserId": "usr_admin",
      "createdAt": "2026-02-17T20:23:00.114Z"
    },
    {
      "id": "3e768d46-a52e-4884-bc01-cc13c2189d95",
      "ticketId": "64e1ca96-0168-46dc-b3a9-160109cbd6d6",
      "type": "STATUS_CHANGED",
      "payload": {
        "from": "doing",
        "to": "done",
        "reason": null
      },
      "actorUserId": "usr_dev",
      "createdAt": "2026-02-17T20:15:07.626Z"
    },
    {
      "id": "5c39adac-134e-4341-9c30-3b447e6e58ac",
      "ticketId": "c03e362a-b88c-420b-b3cf-ec4e897576c0",
      "type": "CREATED",
      "payload": {
        "title": "Chamado comentário 1771359234052"
      },
      "actorUserId": "usr_admin",
      "createdAt": "2026-02-17T20:14:13.680Z"
    },
    {
      "id": "bfc082a7-0e56-43cf-91a9-e139f5b40fc3",
      "ticketId": "2db5ebba-2a9d-4245-bb6d-f912e4081749",
      "type": "CREATED",
      "payload": {
        "title": "Chamado comentário 1771359121961"
      },
      "actorUserId": "usr_admin",
      "createdAt": "2026-02-17T20:12:24.446Z"
    },
    {
      "id": "6be7f372-eaa0-4d63-915c-98b1586fb4dd",
      "ticketId": "4cce90dc-2d8f-4e84-a3d6-4963bdf67824",
      "type": "CREATED",
      "payload": {
        "title": "Chamado comentário 1771358513980"
      },
      "actorUserId": "usr_admin",
      "createdAt": "2026-02-17T20:02:29.099Z"
    },
    {
      "id": "e7a1ced2-af26-422b-8439-e05404cbdcf5",
      "ticketId": "aa70e9cf-9bcc-47f1-ab6d-af8979f8ca69",
      "type": "CREATED",
      "payload": {
        "title": "Chamado comentário 1771358390974"
      },
      "actorUserId": "usr_admin",
      "createdAt": "2026-02-17T20:01:22.855Z"
    },
    {
      "id": "b130cdf8-3a06-448c-9326-eff7113de2f3",
      "ticketId": "35d44daa-7030-4428-a7d3-652b366ab30a",
      "type": "CREATED",
      "payload": {
        "title": "Chamado comentário 1771357166290"
      },
      "actorUserId": "usr_admin",
      "createdAt": "2026-02-17T19:39:39.595Z"
    },
    {
      "id": "c1eab75a-79ae-4bce-b4cc-eba7df0095b4",
      "ticketId": "81cc9087-efc9-49f4-99a9-bda0d02c9113",
      "type": "CREATED",
      "payload": {
        "title": "Chamado comentário 1771357129133"
      },
      "actorUserId": "usr_admin",
      "createdAt": "2026-02-17T19:39:06.959Z"
    },
    {
      "id": "28f08ce0-5448-4b52-984d-fa084480ad20",
      "ticketId": "e1f9e676-cf06-4993-a3b2-b27151a907a9",
      "type": "CREATED",
      "payload": {
        "title": "Chamado comentário 1771356617027"
      },
      "actorUserId": "usr_admin",
      "createdAt": "2026-02-17T19:30:28.865Z"
    },
    {
      "id": "5cf27e46-0431-4000-9787-4763633baab3",
      "ticketId": "50358f1c-68bf-4b83-9f77-cba65ac51af7",
      "type": "CREATED",
      "payload": {
        "title": "Chamado comentário 1771356551574"
      },
      "actorUserId": "usr_admin",
      "createdAt": "2026-02-17T19:29:52.772Z"
    },
    {
      "id": "cc6fec62-05b1-43cf-9948-5716ba22f2e4",
      "ticketId": "16a789c0-789b-4d27-b840-4c1845446a98",
      "type": "CREATED",
      "payload": {
        "title": "Chamado comentário 1771356361871"
      },
      "actorUserId": "usr_admin",
      "createdAt": "2026-02-17T19:26:14.480Z"
    },
    {
      "id": "63c19a98-5299-48c0-8012-40b768c772ed",
      "ticketId": "7d0b0428-d21b-403a-b9e5-dbb0f7a987d5",
      "type": "CREATED",
      "payload": {
        "title": "Chamado comentário 1771356317307"
      },
      "actorUserId": "usr_admin",
      "createdAt": "2026-02-17T19:25:42.044Z"
    },
    {
      "id": "d786a513-04da-4db4-a392-fe98760c94fd",
      "ticketId": "564f4ec7-7d01-4184-8464-20686019f3d7",
      "type": "CREATED",
      "payload": {
        "title": "Chamado comentário 1771356227442"
      },
      "actorUserId": "usr_admin",
      "createdAt": "2026-02-17T19:23:59.174Z"
    },
    {
      "id": "bf2a32a2-b77d-4c50-bf53-8c16e38ed74f",
      "ticketId": "6580090e-7b4a-4391-8465-19d3e58f86b6",
      "type": "CREATED",
      "payload": {
        "title": "Chamado comentário 1771356186549"
      },
      "actorUserId": "usr_admin",
      "createdAt": "2026-02-17T19:23:29.071Z"
    },
    {
      "id": "26c1ca18-5112-4172-87b4-98364f17dec0",
      "ticketId": "06c17bec-c701-4025-9131-925cbb3f1fcf",
      "type": "CREATED",
      "payload": {
        "title": "Chamado comentário 1771356066917"
      },
      "actorUserId": "usr_admin",
      "createdAt": "2026-02-17T19:21:26.843Z"
    },
    {
      "id": "119c8674-8781-44bb-aca1-8d650e6279f2",
      "ticketId": "0770d2e6-5684-4a84-93bb-3fd67c94196d",
      "type": "CREATED",
      "payload": {
        "title": "Chamado comentário 1771356010215"
      },
      "actorUserId": "usr_admin",
      "createdAt": "2026-02-17T19:20:45.867Z"
    },
    {
      "id": "552e204f-22f1-4770-b26f-9ca9c2c060fd",
      "ticketId": "4ba31d91-ea9d-41c9-b6e9-24524ef5aa1f",
      "type": "CREATED",
      "payload": {
        "title": "Chamado comentário 1771355487523"
      },
      "actorUserId": "usr_admin",
      "createdAt": "2026-02-17T19:11:41.265Z"
    },
    {
      "id": "955fe2b9-087b-4a73-93f7-e5a352b3d8c1",
      "ticketId": "b03628cb-c2e3-4961-a1a2-9a3b448e429a",
      "type": "CREATED",
      "payload": {
        "title": "Chamado comentário 1771355449948"
      },
      "actorUserId": "usr_admin",
      "createdAt": "2026-02-17T19:11:07.804Z"
    },
    {
      "id": "0fd7d171-f3ea-498c-b7b9-4b03d174ee95",
      "ticketId": "25f701bc-2370-4b5f-bb11-473439cee43b",
      "type": "ASSIGNED",
      "payload": {
        "from": null,
        "to": "usr_itdev"
      },
      "actorUserId": null,
      "createdAt": "2026-02-17T19:08:46.405Z"
    },
    {
      "id": "fb5ea647-7745-47ca-b29e-ded8ca0f0e7b",
      "ticketId": "25f701bc-2370-4b5f-bb11-473439cee43b",
      "type": "CREATED",
      "payload": {
        "title": "Chamado comentário 1771355255040"
      },
      "actorUserId": "usr_admin",
      "createdAt": "2026-02-17T19:07:48.209Z"
    },
    {
      "id": "3a9bed43-8c55-4afc-b0de-0aa51c4cbe4e",
      "ticketId": "cbb93097-7170-461a-8845-b3552fcf8bdf",
      "type": "COMMENT_ADDED",
      "payload": {
        "commentId": "cd2fa1eb-45b7-4460-a517-82ceec33fb3b"
      },
      "actorUserId": "usr_admin",
      "createdAt": "2026-02-17T19:07:13.942Z"
    },
    {
      "id": "e4cff823-6cc1-4f49-bd7a-a2d614c7f806",
      "ticketId": "cbb93097-7170-461a-8845-b3552fcf8bdf",
      "type": "CREATED",
      "payload": {
        "title": "Chamado comentário 1771355153644"
      },
      "actorUserId": "usr_admin",
      "createdAt": "2026-02-17T19:06:20.286Z"
    },
    {
      "id": "a8f8fccf-695c-41af-bf3c-8437140249d8",
      "ticketId": "af1cd7e5-2015-4c53-b6d1-cb52c48ab28a",
      "type": "CREATED",
      "payload": {
        "title": "Chamado comentário 1771354960362"
      },
      "actorUserId": "usr_admin",
      "createdAt": "2026-02-17T19:02:51.665Z"
    },
    {
      "id": "b591b7f8-915d-46cd-b792-b92d701ab0b9",
      "ticketId": "c4f5ee7d-29b5-4526-94a3-743460e8c70f",
      "type": "REACTION_ADDED",
      "payload": {
        "commentId": "ecb5d079-5dbd-4b23-bbef-45daf4ebb714",
        "type": "like"
      },
      "actorUserId": "usr_admin",
      "createdAt": "2026-02-17T19:02:16.537Z"
    },
    {
      "id": "182d83db-0311-4021-9a37-3b3ccd32ef6b",
      "ticketId": "c4f5ee7d-29b5-4526-94a3-743460e8c70f",
      "type": "COMMENT_ADDED",
      "payload": {
        "commentId": "ecb5d079-5dbd-4b23-bbef-45daf4ebb714"
      },
      "actorUserId": "usr_admin",
      "createdAt": "2026-02-17T19:01:57.479Z"
    },
    {
      "id": "13d53055-43d1-47e6-9708-1b2a12af4a90",
      "ticketId": "c4f5ee7d-29b5-4526-94a3-743460e8c70f",
      "type": "CREATED",
      "payload": {
        "title": "Chamado comentário 1771354860725"
      },
      "actorUserId": "usr_admin",
      "createdAt": "2026-02-17T19:01:29.565Z"
    },
    {
      "id": "f9fbfbae-54f2-4972-bb0a-6ca81187dd6c",
      "ticketId": "50a8372e-87ef-4669-b5ae-36f9d77608b9",
      "type": "COMMENT_ADDED",
      "payload": {
        "commentId": "ab3eb666-dec8-4dce-ad71-28efafa04e64"
      },
      "actorUserId": "usr_admin",
      "createdAt": "2026-02-17T18:59:33.454Z"
    },
    {
      "id": "81010ca8-8243-4da3-ac5f-36035e8bdb2c",
      "ticketId": "50a8372e-87ef-4669-b5ae-36f9d77608b9",
      "type": "CREATED",
      "payload": {
        "title": "Chamado comentário 1771354712024"
      },
      "actorUserId": "usr_admin",
      "createdAt": "2026-02-17T18:58:56.539Z"
    },
    {
      "id": "f8b67569-11d6-4c9c-be0e-dad598a480eb",
      "ticketId": "16629048-7fe4-4339-a82b-4c87b45396cd",
      "type": "REACTION_ADDED",
      "payload": {
        "commentId": "b392eec7-28b8-4a51-8659-84f978e2bfd8",
        "type": "like"
      },
      "actorUserId": "usr_admin",
      "createdAt": "2026-02-17T18:57:34.714Z"
    },
    {
      "id": "98e5da06-f83a-4bef-a537-af258f80150c",
      "ticketId": "16629048-7fe4-4339-a82b-4c87b45396cd",
      "type": "COMMENT_ADDED",
      "payload": {
        "commentId": "b392eec7-28b8-4a51-8659-84f978e2bfd8"
      },
      "actorUserId": "usr_admin",
      "createdAt": "2026-02-17T18:57:26.934Z"
    },
    {
      "id": "0d95ea27-50a0-4a36-a178-f6bfc077470a",
      "ticketId": "16629048-7fe4-4339-a82b-4c87b45396cd",
      "type": "CREATED",
      "payload": {
        "title": "Chamado comentário 1771354609344"
      },
      "actorUserId": "usr_admin",
      "createdAt": "2026-02-17T18:57:16.165Z"
    },
    {
      "id": "991e077a-5d23-4d26-a6bd-b845993e5f57",
      "ticketId": "2b1ce038-c4bc-43cd-bb20-24ce13935ff5",
      "type": "CREATED",
      "payload": {
        "title": "Chamado comentário 1771354464418"
      },
      "actorUserId": "usr_admin",
      "createdAt": "2026-02-17T18:54:36.600Z"
    },
    {
      "id": "e9b34daf-618d-4cf5-8f94-31ca0a747bbd",
      "ticketId": "bef4fb91-545e-486b-ab22-bbfad761f96d",
      "type": "CREATED",
      "payload": {
        "title": "Chamado comentário 1771354408212"
      },
      "actorUserId": "usr_admin",
      "createdAt": "2026-02-17T18:54:04.255Z"
    },
    {
      "id": "dfb128c1-d208-4002-be7b-62453d6f439a",
      "ticketId": "54aa60a8-396e-42e0-8f21-102e9e864577",
      "type": "CREATED",
      "payload": {
        "title": "Chamado comentário 1771353732174"
      },
      "actorUserId": "usr_admin",
      "createdAt": "2026-02-17T18:42:24.457Z"
    },
    {
      "id": "12cd7f5f-b34b-4665-ac63-d8846a1f98c0",
      "ticketId": "308a72eb-6ced-49eb-bf39-da8634ac9244",
      "type": "COMMENT_ADDED",
      "payload": {
        "commentId": "c9c8400b-2198-4f54-80d9-2c12ad2131c0"
      },
      "actorUserId": "usr_admin",
      "createdAt": "2026-02-17T18:41:15.946Z"
    },
    {
      "id": "4c1968b6-f479-4677-81b4-bca39d5c1bc8",
      "ticketId": "308a72eb-6ced-49eb-bf39-da8634ac9244",
      "type": "CREATED",
      "payload": {
        "title": "Chamado comentário 1771353632489"
      },
      "actorUserId": "usr_admin",
      "createdAt": "2026-02-17T18:40:59.098Z"
    },
    {
      "id": "fb68f963-d25a-4f5c-8228-b901b4e08ad5",
      "ticketId": "a57af743-5a82-4ad0-b7ed-64c519993077",
      "type": "CREATED",
      "payload": {
        "title": "Chamado comentário 1771353513928"
      },
      "actorUserId": "usr_admin",
      "createdAt": "2026-02-17T18:38:54.527Z"
    },
    {
      "id": "782c32b2-a0e0-4a02-b70f-3bcfc284fc42",
      "ticketId": "17462073-ebc3-4c90-9595-e0b44d7257e5",
      "type": "UPDATED",
      "payload": {
        "title": "Chamado comentário 1771353414539 sdd",
        "type": "melhoria",
        "priority": "medium",
        "tags": []
      },
      "actorUserId": "usr_admin",
      "createdAt": "2026-02-17T18:37:58.143Z"
    },
    {
      "id": "c13c2cf3-d024-49bf-8a00-b45000463d6c",
      "ticketId": "17462073-ebc3-4c90-9595-e0b44d7257e5",
      "type": "COMMENT_ADDED",
      "payload": {
        "commentId": "87f45123-3e3a-4d6b-9b41-78eddf5a034f"
      },
      "actorUserId": "usr_admin",
      "createdAt": "2026-02-17T18:37:28.668Z"
    },
    {
      "id": "5e494888-8fda-4b45-960e-11e1b0573231",
      "ticketId": "17462073-ebc3-4c90-9595-e0b44d7257e5",
      "type": "CREATED",
      "payload": {
        "title": "Chamado comentário 1771353414539"
      },
      "actorUserId": "usr_admin",
      "createdAt": "2026-02-17T18:37:18.397Z"
    },
    {
      "id": "bc439fe2-f35e-4122-919e-52a30943f7fb",
      "ticketId": "b06edd1e-6512-46d1-97b5-0f780b67e125",
      "type": "COMMENT_DELETED",
      "payload": {
        "commentId": "cfbb6d9e-fea9-4c38-bdae-2b27dfd30d12"
      },
      "actorUserId": "usr_admin",
      "createdAt": "2026-02-17T18:33:21.902Z"
    },
    {
      "id": "29712708-0d3c-497a-9001-7ec67610cd69",
      "ticketId": "b06edd1e-6512-46d1-97b5-0f780b67e125",
      "type": "COMMENT_UPDATED",
      "payload": {
        "commentId": "cfbb6d9e-fea9-4c38-bdae-2b27dfd30d12"
      },
      "actorUserId": "usr_admin",
      "createdAt": "2026-02-17T18:33:15.768Z"
    },
    {
      "id": "000936f7-b945-4af3-aeef-fc2c13daab9e",
      "ticketId": "b06edd1e-6512-46d1-97b5-0f780b67e125",
      "type": "COMMENT_ADDED",
      "payload": {
        "commentId": "cfbb6d9e-fea9-4c38-bdae-2b27dfd30d12"
      },
      "actorUserId": "usr_admin",
      "createdAt": "2026-02-17T18:33:11.083Z"
    },
    {
      "id": "fc677270-919e-45e9-b93e-b2f2a057a523",
      "ticketId": "b06edd1e-6512-46d1-97b5-0f780b67e125",
      "type": "REACTION_ADDED",
      "payload": {
        "commentId": "3a728674-ee0d-42dd-9d0b-b5ebd15826c2",
        "type": "like"
      },
      "actorUserId": "usr_admin",
      "createdAt": "2026-02-17T18:33:07.771Z"
    },
    {
      "id": "91142240-079e-45a8-a1e7-d1ecd1886f18",
      "ticketId": "b06edd1e-6512-46d1-97b5-0f780b67e125",
      "type": "COMMENT_ADDED",
      "payload": {
        "commentId": "3a728674-ee0d-42dd-9d0b-b5ebd15826c2"
      },
      "actorUserId": "usr_admin",
      "createdAt": "2026-02-17T18:33:04.887Z"
    },
    {
      "id": "adddf47f-a4b0-4d64-8d92-bd91a23b6035",
      "ticketId": "b06edd1e-6512-46d1-97b5-0f780b67e125",
      "type": "CREATED",
      "payload": {
        "title": "Chamado comentário 1771353154000"
      },
      "actorUserId": "usr_admin",
      "createdAt": "2026-02-17T18:32:49.293Z"
    },
    {
      "id": "634c6ad5-b4e1-43a7-a875-6f95016a4995",
      "ticketId": "e71fa065-491e-4e36-ab80-a9418b81f40f",
      "type": "COMMENT_UPDATED",
      "payload": {
        "commentId": "84112ec7-71ea-42af-be8b-256f24f95691"
      },
      "actorUserId": "usr_admin",
      "createdAt": "2026-02-17T18:31:40.495Z"
    },
    {
      "id": "95285f06-7478-4968-85a3-3675d10277d2",
      "ticketId": "e71fa065-491e-4e36-ab80-a9418b81f40f",
      "type": "REACTION_ADDED",
      "payload": {
        "commentId": "84112ec7-71ea-42af-be8b-256f24f95691",
        "type": "like"
      },
      "actorUserId": "usr_admin",
      "createdAt": "2026-02-17T18:31:31.956Z"
    },
    {
      "id": "3a236ef0-0fc5-4814-ab63-b6bc6e995e4d",
      "ticketId": "e71fa065-491e-4e36-ab80-a9418b81f40f",
      "type": "COMMENT_ADDED",
      "payload": {
        "commentId": "84112ec7-71ea-42af-be8b-256f24f95691"
      },
      "actorUserId": "usr_admin",
      "createdAt": "2026-02-17T18:31:24.631Z"
    },
    {
      "id": "40d3b7c7-a180-49fb-8efc-498c3c9b7b4b",
      "ticketId": "e71fa065-491e-4e36-ab80-a9418b81f40f",
      "type": "CREATED",
      "payload": {
        "title": "Chamado comentário 1771353047417"
      },
      "actorUserId": "usr_admin",
      "createdAt": "2026-02-17T18:31:17.552Z"
    },
    {
      "id": "de907d85-43d7-48aa-a600-dba21be20c0c",
      "ticketId": "f024f2b1-805c-42ee-b628-cfaa5395cbb9",
      "type": "CREATED",
      "payload": {
        "title": "Chamado comentário 1771352890522"
      },
      "actorUserId": "usr_admin",
      "createdAt": "2026-02-17T18:28:34.881Z"
    },
    {
      "id": "bd23de91-fea1-4bee-a952-cd3e0fcef657",
      "ticketId": "5b729f60-a279-4e6b-81d2-f984eaceed62",
      "type": "CREATED",
      "payload": {
        "title": "Chamado comentário 1771352726947"
      },
      "actorUserId": "usr_admin",
      "createdAt": "2026-02-17T18:25:55.037Z"
    },
    {
      "id": "46b29bf5-5637-4a9a-8c71-67b2776b9148",
      "ticketId": "9f618d99-1da1-462a-b452-f8826687bb17",
      "type": "CREATED",
      "payload": {
        "title": "Chamado comentário 1771352592617"
      },
      "actorUserId": "usr_admin",
      "createdAt": "2026-02-17T18:23:25.012Z"
    },
    {
      "id": "f5734335-ac14-4d19-9d25-cfdeb818fe7d",
      "ticketId": "5eaa3010-fd7f-47ed-be05-fc0810d44917",
      "type": "CREATED",
      "payload": {
        "title": "Chamado comentário 1771352493166"
      },
      "actorUserId": "usr_admin",
      "createdAt": "2026-02-17T18:22:03.092Z"
    },
    {
      "id": "86b6a5a1-e89a-432f-bb77-8a03cc038600",
      "ticketId": "56a32fc9-b3ca-432c-8015-aadadfe41830",
      "type": "CREATED",
      "payload": {
        "title": "Chamado comentário 1771352456530"
      },
      "actorUserId": "usr_admin",
      "createdAt": "2026-02-17T18:21:18.256Z"
    },
    {
      "id": "631d21b3-dd5a-47bc-bfad-c8ad105fb80a",
      "ticketId": "f16d3294-c926-4c46-8082-4ac2fec76fa4",
      "type": "CREATED",
      "payload": {
        "title": "Chamado comentário 1771352399088"
      },
      "actorUserId": "usr_admin",
      "createdAt": "2026-02-17T18:20:18.371Z"
    },
    {
      "id": "3fb33b08-7f11-42a2-9124-576a6a33321b",
      "ticketId": "d6a87943-2f56-4aaf-9f50-476679dbda1e",
      "type": "CREATED",
      "payload": {
        "title": "Chamado comentário 1771352376143"
      },
      "actorUserId": "usr_admin",
      "createdAt": "2026-02-17T18:19:45.060Z"
    },
    {
      "id": "2a7a3681-55e6-4c65-868f-074f83de0bdd",
      "ticketId": "dca028dc-5511-4b68-a641-6df5db0e3d41",
      "type": "CREATED",
      "payload": {
        "title": "Chamado comentário 1771352200310"
      },
      "actorUserId": "usr_admin",
      "createdAt": "2026-02-17T18:17:00.796Z"
    },
    {
      "id": "db35ba5d-356e-4455-a08d-ea0ff4206543",
      "ticketId": "c9af7544-bdc2-4108-99f0-fb2bbd31accd",
      "type": "CREATED",
      "payload": {
        "title": "Chamado comentário 1771352106437"
      },
      "actorUserId": "usr_admin",
      "createdAt": "2026-02-17T18:15:23.048Z"
    },
    {
      "id": "70643806-8b1a-4bec-a963-52f509c76fce",
      "ticketId": "4272ca09-956d-4fc4-b4f3-1a4cb1cd20e7",
      "type": "CREATED",
      "payload": {
        "title": "Chamado comentário 1771351967486"
      },
      "actorUserId": "usr_admin",
      "createdAt": "2026-02-17T18:13:11.856Z"
    },
    {
      "id": "706c0d58-d762-4036-8e9e-96dd1842bdbe",
      "ticketId": "26676d1c-d741-4e4a-9e27-e38dc4127960",
      "type": "CREATED",
      "payload": {
        "title": "Chamado comentário 1771351873529"
      },
      "actorUserId": "usr_admin",
      "createdAt": "2026-02-17T18:11:27.591Z"
    },
    {
      "id": "b49c0287-bb6c-408e-9eb3-27d6d45c3d23",
      "ticketId": "5751e31f-f7d9-416c-92ce-5d19f3d31840",
      "type": "CREATED",
      "payload": {
        "title": "Chamado comentário 1771351706987"
      },
      "actorUserId": "usr_admin",
      "createdAt": "2026-02-17T18:08:57.545Z"
    },
    {
      "id": "10725670-a08f-4cb4-85d4-4f876ffaf15c",
      "ticketId": "6900908c-9586-44e7-9d1c-e436a525022a",
      "type": "CREATED",
      "payload": {
        "title": "Chamado comentário 1771351610074"
      },
      "actorUserId": "usr_admin",
      "createdAt": "2026-02-17T18:07:08.547Z"
    },
    {
      "id": "983e8fbe-f3a9-4ef5-8f35-d9131ffe3a42",
      "ticketId": "aab2f216-b863-420f-976a-b8a518ff09a1",
      "type": "CREATED",
      "payload": {
        "title": "Chamado comentário 1771351199454"
      },
      "actorUserId": "usr_admin",
      "createdAt": "2026-02-17T18:00:10.732Z"
    },
    {
      "id": "b08447fd-653b-4173-9ec6-29e5920ce6fa",
      "ticketId": "d6d9013f-d17b-4e62-82a5-751a2102791e",
      "type": "CREATED",
      "payload": {
        "title": "Chamado comentário 1771351141778"
      },
      "actorUserId": "usr_admin",
      "createdAt": "2026-02-17T17:59:23.436Z"
    },
    {
      "id": "4d660c91-a59e-4cee-b65e-d2d1af43b9b6",
      "ticketId": "d5474442-f12c-423d-9346-eb585c9ad56b",
      "type": "CREATED",
      "payload": {
        "title": "Chamado comentário 1771350998984"
      },
      "actorUserId": "usr_admin",
      "createdAt": "2026-02-17T17:56:51.174Z"
    },
    {
      "id": "623df03b-3cf5-49f1-ac36-93c9866e286b",
      "ticketId": "bd67cbe4-3f1e-4a34-ba9a-6a8bc7a57147",
      "type": "CREATED",
      "payload": {
        "title": "fgfd"
      },
      "actorUserId": "usr_admin",
      "createdAt": "2026-02-17T17:56:22.569Z"
    },
    {
      "id": "ebea8bf4-0f1c-43f3-b4db-aae06466bd57",
      "ticketId": "eeb00a60-6e88-4d30-a055-7d1d08a3bea4",
      "type": "CREATED",
      "payload": {
        "title": "Chamado comentário 1771350937818"
      },
      "actorUserId": "usr_admin",
      "createdAt": "2026-02-17T17:56:00.786Z"
    },
    {
      "id": "f1098064-07f6-45ed-9abc-6dde94a4b533",
      "ticketId": "0538f0d6-b41e-47da-b15a-b15efe2a8f89",
      "type": "CREATED",
      "payload": {
        "title": "Chamado comentário 1771350814535"
      },
      "actorUserId": "usr_admin",
      "createdAt": "2026-02-17T17:53:46.045Z"
    },
    {
      "id": "c18131c0-da72-4abb-b427-5c6b3f817fda",
      "ticketId": "8c0506ea-44e1-460f-8e2b-27124a9bac5e",
      "type": "CREATED",
      "payload": {
        "title": "Chamado comentário 1771350772966"
      },
      "actorUserId": "usr_admin",
      "createdAt": "2026-02-17T17:53:09.494Z"
    },
    {
      "id": "d02420ec-cacb-4fd6-9147-56bc313c5bf6",
      "ticketId": "64e1ca96-0168-46dc-b3a9-160109cbd6d6",
      "type": "STATUS_CHANGED",
      "payload": {
        "from": "backlog",
        "to": "doing",
        "reason": null
      },
      "actorUserId": "usr_dev",
      "createdAt": "2026-02-17T17:44:34.427Z"
    },
    {
      "id": "43602619-270c-46fa-b6cc-1617686c17a7",
      "ticketId": "28d3f8fa-a261-49ee-a8c6-706f51f5764f",
      "type": "STATUS_CHANGED",
      "payload": {
        "from": "review",
        "to": "doing",
        "reason": null
      },
      "actorUserId": "usr_dev",
      "createdAt": "2026-02-17T17:44:08.101Z"
    },
    {
      "id": "3377f6e5-aee6-4a6d-a7cc-874b4f112d8b",
      "ticketId": "724d3ec1-2e09-430c-b3fe-a8e7c84fc5c8",
      "type": "STATUS_CHANGED",
      "payload": {
        "from": "doing",
        "to": "review",
        "reason": null
      },
      "actorUserId": "usr_dev",
      "createdAt": "2026-02-17T17:38:24.081Z"
    },
    {
      "id": "816e89a0-41fa-4b3b-8d45-0dff72209189",
      "ticketId": "bb922bb0-7495-42c0-bbcd-c30a5a2639d0",
      "type": "STATUS_CHANGED",
      "payload": {
        "from": "backlog",
        "to": "done",
        "reason": null
      },
      "actorUserId": "usr_dev",
      "createdAt": "2026-02-17T17:38:09.281Z"
    },
    {
      "id": "a481a41f-811f-41ac-9025-734d25158194",
      "ticketId": "25bf457b-7fbe-4ca3-8670-914d9ab15be4",
      "type": "STATUS_CHANGED",
      "payload": {
        "from": "doing",
        "to": "review",
        "reason": null
      },
      "actorUserId": "usr_dev",
      "createdAt": "2026-02-17T17:37:49.714Z"
    },
    {
      "id": "fe42601c-5608-4589-b8a3-3111a48e45f2",
      "ticketId": "28d3f8fa-a261-49ee-a8c6-706f51f5764f",
      "type": "STATUS_CHANGED",
      "payload": {
        "from": "backlog",
        "to": "review",
        "reason": null
      },
      "actorUserId": "usr_dev",
      "createdAt": "2026-02-17T17:23:00.274Z"
    },
    {
      "id": "12bce10e-5454-4055-8777-89bad9512361",
      "ticketId": "6dddbb37-9efe-4705-9afd-05a9f82ba4fa",
      "type": "STATUS_CHANGED",
      "payload": {
        "from": "review",
        "to": "doing",
        "reason": null
      },
      "actorUserId": "usr_dev",
      "createdAt": "2026-02-17T17:22:58.151Z"
    },
    {
      "id": "ea02be72-ba17-4de7-964d-f22dd2ed148b",
      "ticketId": "724d3ec1-2e09-430c-b3fe-a8e7c84fc5c8",
      "type": "STATUS_CHANGED",
      "payload": {
        "from": "review",
        "to": "doing",
        "reason": null
      },
      "actorUserId": "usr_dev",
      "createdAt": "2026-02-17T17:22:56.153Z"
    },
    {
      "id": "dae6e21e-cd38-4208-a10e-5c8a8842ac01",
      "ticketId": "28d3f8fa-a261-49ee-a8c6-706f51f5764f",
      "type": "CREATED",
      "payload": {
        "title": "Automated chamado admin-1771348889475"
      },
      "actorUserId": "usr_admin",
      "createdAt": "2026-02-17T17:21:41.085Z"
    },
    {
      "id": "5a5c87c1-b0be-4f3c-99bf-1593cf5d17cb",
      "ticketId": "64e1ca96-0168-46dc-b3a9-160109cbd6d6",
      "type": "CREATED",
      "payload": {
        "title": "Automated chamado admin-1771348831481"
      },
      "actorUserId": "usr_admin",
      "createdAt": "2026-02-17T17:20:54.325Z"
    },
    {
      "id": "116973bb-1469-42f1-bf83-20f29d6fdd2c",
      "ticketId": "fd0dcfe7-00e6-4595-ae7b-c5c794b4b947",
      "type": "STATUS_CHANGED",
      "payload": {
        "from": "review",
        "to": "done",
        "reason": null
      },
      "actorUserId": "usr_dev",
      "createdAt": "2026-02-17T17:19:23.859Z"
    },
    {
      "id": "eff7e6f4-f418-4282-bf1f-b17de6bb7784",
      "ticketId": "f8e6f16a-432f-43bc-8001-5d2ded489f63",
      "type": "STATUS_CHANGED",
      "payload": {
        "from": "doing",
        "to": "done",
        "reason": null
      },
      "actorUserId": "usr_dev",
      "createdAt": "2026-02-17T17:19:19.541Z"
    },
    {
      "id": "607c8bca-48ec-4de8-851a-63aeecc98c1f",
      "ticketId": "d11ad926-343d-4b8f-89ac-6e69f337514b",
      "type": "STATUS_CHANGED",
      "payload": {
        "from": "backlog",
        "to": "doing",
        "reason": null
      },
      "actorUserId": "usr_dev",
      "createdAt": "2026-02-17T17:18:58.329Z"
    },
    {
      "id": "729f371d-23a9-488a-b2f8-3a3b50462cfe",
      "ticketId": "6dddbb37-9efe-4705-9afd-05a9f82ba4fa",
      "type": "STATUS_CHANGED",
      "payload": {
        "from": "backlog",
        "to": "review",
        "reason": null
      },
      "actorUserId": "usr_dev",
      "createdAt": "2026-02-17T17:18:56.152Z"
    },
    {
      "id": "443c31c8-7270-468d-9279-bb496f8d4219",
      "ticketId": "19bc4a44-2c53-4fab-968d-f00e3333a251",
      "type": "STATUS_CHANGED",
      "payload": {
        "from": "backlog",
        "to": "doing",
        "reason": null
      },
      "actorUserId": "usr_dev",
      "createdAt": "2026-02-17T17:18:54.535Z"
    },
    {
      "id": "44d53396-bde1-40c6-b8d4-9b3d67244f26",
      "ticketId": "724d3ec1-2e09-430c-b3fe-a8e7c84fc5c8",
      "type": "STATUS_CHANGED",
      "payload": {
        "from": "backlog",
        "to": "review",
        "reason": null
      },
      "actorUserId": "usr_dev",
      "createdAt": "2026-02-17T17:18:52.700Z"
    },
    {
      "id": "2201d94c-1855-416e-8c7d-bb4b47ae977a",
      "ticketId": "25bf457b-7fbe-4ca3-8670-914d9ab15be4",
      "type": "STATUS_CHANGED",
      "payload": {
        "from": "backlog",
        "to": "doing",
        "reason": null
      },
      "actorUserId": "usr_dev",
      "createdAt": "2026-02-17T17:18:51.021Z"
    }
  ]
}